LICENSE
MANIFEST.in
README.md
requirements.txt
setup.py
useful/logs/__init__.py
useful/logs/_context.py
useful/logs/_json_logging.py
useful/logs/_setup.py
useful/logs/exception_hooks.py
useful/logs/version.py
velebit_useful_logs.egg-info/PKG-INFO
velebit_useful_logs.egg-info/SOURCES.txt
velebit_useful_logs.egg-info/dependency_links.txt
velebit_useful_logs.egg-info/top_level.txt