Metadata-Version: 2.1
Name: velebit-useful-logs
Version: 1.0.2
Summary: Module for standardized logs across services
Home-page: https://github.com/velebit-ai/useful-logs
Author: Velebit AI
Author-email: contact@velebit.ai
License: UNKNOWN
Platform: UNKNOWN
Classifier: License :: OSI Approved :: MIT License
Classifier: Programming Language :: Python :: 3
Classifier: Programming Language :: Python :: 3.6
Classifier: Programming Language :: Python :: 3.7
Classifier: Programming Language :: Python :: 3.8
License-File: LICENSE
